salesforce_basic.py
salesforce_basic-0.10.dist-info/METADATA
salesforce_basic-0.10.dist-info/WHEEL
salesforce_basic-0.10.dist-info/top_level.txt
salesforce_basic-0.10.dist-info/RECORD
